{
	"customers": [
      {
        "id": "1",
        "name": "Ashok Adhikari",
        "email": "ashok.adhikari92@gmail.com",
        "age": 25
      },
      {
        "id": "2",
        "name": "Madhu Sudhan Subedi",
        "email": "madhusudhan@gmail.com",
        "age": 23
      },
      {
        "id": "3",
        "name": "Ramesh Pandey",
        "email": "rameshpandey@gmail.com",
        "age": 21
      },
      {
        "id": "4",
        "name": "Niraj Adhikari",
        "email": "nirajadhikari@gmail.com",
        "age": 23
      },
      {
        "id": "5",
        "name": "Anil Adhikari",
        "email": "aniladhikari@gmail.com",
        "age": 20
      }
    ]
}